FencingChallenge/__init__.py
FencingChallenge/board_new.py
FencingChallenge/pentomino_cv.py
FencingChallenge/pentominos.py
FenceChallenge-0.0.1.dist-info/METADATA
FenceChallenge-0.0.1.dist-info/WHEEL
FenceChallenge-0.0.1.dist-info/top_level.txt
FenceChallenge-0.0.1.dist-info/RECORD
